{
  "name": "2025-03-17-21-08-v1.3.0-genesis",
  "env": "testnet-sepolia",
  "segmentId": 4,
  "segments": [
    {
      "type": "eoa",
      "filename": "1-deploy.s.sol",
      "id": 0
    },
    {
      "type": "multisig",
      "filename": "2-queue.s.sol",
      "id": 1
    },
    {
      "type": "multisig",
      "filename": "3-execute.s.sol",
      "id": 2
    },
    {
      "type": "multisig",
      "filename": "4-disable-eigenpods.s.sol",
      "id": 3
    },
    {
      "type": "multisig",
      "filename": "5-strategies.s.sol",
      "id": 4
    }
  ],
  "metadata": [
    {
      "type": "eoa",
      "signer": "0xD39A1922fBe6c083f7A2d02CA05eA7bE2af52bA8",
      "transactions": [],
      "deployments": [
        {
          "address": "0xe09BB3e1c8BB31557AB787b91Ee9b490C14F0420",
          "contract": "DelegationManager_Proxy",
          "singleton": true
        },
        {
          "address": "0x89d7b7596C788C5f2e8B6aBC969A5f4B44DE50bb",
          "contract": "StrategyManager_Proxy",
          "singleton": true
        },
        {
          "address": "0x995A7532013179070DA212787107de57A7ACA5aa",
          "contract": "StrategyFactory_Proxy",
          "singleton": true
        },
        {
          "address": "0xdB5b3bA1D3eA683ed409b8b2E8C21439a10B0D49",
          "contract": "AVSDirectory_Proxy",
          "singleton": true
        },
        {
          "address": "0x4953BEdc3dbD97E59fCF9cbA24870d8c5D1ed88f",
          "contract": "AllocationManager_Proxy",
          "singleton": true
        },
        {
          "address": "0x92Cd67bDd1D1f07AaA053EE438E6f972A0CE8f98",
          "contract": "RewardsCoordinator_Proxy",
          "singleton": true
        },
        {
          "address": "0xEa457b720726D373bA6E7A59ee552882DE5DcC31",
          "contract": "EigenPodManager_Proxy",
          "singleton": true
        },
        {
          "address": "0x74e1C5773fFBfef872E5f35F2344F5f22DDAc968",
          "contract": "EigenPod_Proxy",
          "singleton": true
        },
        {
          "address": "0x501171Ab29592Db15e1fCAbCdd373b54df2c123e",
          "contract": "PermissionController_Proxy",
          "singleton": true
        },
        {
          "address": "0xa64E42B6fA9053A55004Ee30733228FBd16094c2",
          "contract": "EigenPod_Impl",
          "singleton": true
        },
        {
          "address": "0x3CC00A0630429BC38b7A67ea57FdD7dfaDf43BFB",
          "contract": "EigenPod_Beacon",
          "singleton": true
        },
        {
          "address": "0x4Db96CC892075A6c10b75EDC5Eb2A2FDBAf2f678",
          "contract": "PauserRegistry_Impl",
          "singleton": true
        },
        {
          "address": "0xf3e5e5105625fd4235A1E98EFd15c994C1622FE5",
          "contract": "DelegationManager_Impl",
          "singleton": true
        },
        {
          "address": "0xcCDae30Fd2cB865178c3893bcf38efF385a207ab",
          "contract": "StrategyManager_Impl",
          "singleton": true
        },
        {
          "address": "0x6B38bC31454649661cA0b35fb9f934ae4f75434F",
          "contract": "AVSDirectory_Impl",
          "singleton": true
        },
        {
          "address": "0xB5866280e276Bfc8c411186c05A6dF5772D17706",
          "contract": "EigenPodManager_Impl",
          "singleton": true
        },
        {
          "address": "0x10FDCE9CE6d1B9bb1BB5551234Ba3583a732582d",
          "contract": "RewardsCoordinator_Impl",
          "singleton": true
        },
        {
          "address": "0x8CFd1E92a3658a3D3961AeCA83ff457A1ca162A0",
          "contract": "AllocationManager_Impl",
          "singleton": true
        },
        {
          "address": "0xa3E18eA31A77e917370076efFC19C20473E34f11",
          "contract": "PermissionController_Impl",
          "singleton": true
        },
        {
          "address": "0x3CabC6A1CB2A70198c3D02Ed7C51be64514799fb",
          "contract": "StrategyFactory_Impl",
          "singleton": true
        },
        {
          "address": "0x0a216178f963bD77f849dE82Df8c3C0Afa5D1502",
          "contract": "StrategyBaseTVLLimits_Impl",
          "singleton": true
        },
        {
          "address": "0x401FEE51Fd707cf3E995dA70590D39E73a7f862d",
          "contract": "EigenStrategy_Impl",
          "singleton": true
        },
        {
          "address": "0x1582bA10675CF4c36Be6Dc8c16a61B63dFae58F3",
          "contract": "StrategyBase_Impl",
          "singleton": true
        },
        {
          "address": "0x9009E2c51e75483aA45542a22B24E3a1AbF1004c",
          "contract": "StrategyBase_Beacon",
          "singleton": true
        }
      ],
      "confirmed": true
    },
    {
      "type": "multisig",
      "signer": "0xD39A1922fBe6c083f7A2d02CA05eA7bE2af52bA8",
      "signerType": "gnosis.onchain",
      "gnosisTransactionHash": "0x6fab1d26047459a12aca278bee76bbf79fdd5522971b8f92ebefbea27eddba8d",
      "multisig": "0x6e8720B32f216d8cB8277A501f3c5Dadc1c5F1De",
      "confirmed": true,
      "immediateExecutionHash": "0x2e0939c3dfbf644a64e612da95eff7630558aba063ab04a6a02af8f350602f0a"
    },
    {
      "type": "multisig",
      "signer": "0xD39A1922fBe6c083f7A2d02CA05eA7bE2af52bA8",
      "signerType": "gnosis.onchain",
      "gnosisTransactionHash": "0x3d211be62ce050abcb0b64a0dfbd8897b39897f804651490bc4fef2ce7202364",
      "multisig": "0x6e8720B32f216d8cB8277A501f3c5Dadc1c5F1De",
      "confirmed": true,
      "immediateExecutionHash": "0x3efc6572ea7e53862ae093a399612ad526008b69fd2d1d3a0c7c397c98aacc94"
    },
    {
      "type": "multisig",
      "signer": "0xD39A1922fBe6c083f7A2d02CA05eA7bE2af52bA8",
      "signerType": "gnosis.onchain",
      "gnosisTransactionHash": "0x5ae9a65d91c915710040a51c469ae948b0c75407f5702572c2c006d602b37396",
      "multisig": "0x85F6f4d4110EeCC6Fe066Eb1335675717D848027",
      "confirmed": true,
      "immediateExecutionHash": "0x2821675d603e95ff5cc1ba5fb5d639f1eb9085bc16cb1745ba93a76058553864"
    }
  ],
  "upgrade": "v1.3.0-genesis",
  "upgradePath": "script/releases/v1.3.0-genesis",
  "phase": "eoa_validate",
  "chainId": 11155111,
  "startTime": "Mon Mar 17 2025 21:08:25 GMT-0400 (Eastern Daylight Time)",
  "startTimestamp": 1742260105.468
}
